{
    "version": "5.16.6",
    "description": "Galgame翻译工具, 支持剪贴板, OCR, HOOK, 支持30余种翻译工具, 支持TTS",
    "homepage": "https://github.com/HIllya51/LunaTranslator",
    "license": "GPL-3.0-only",
    "url": "https://github.com/HIllya51/LunaTranslator/releases/download/v5.16.6/LunaTranslator.zip",
    "hash": "9e59df630a3748a843d8a9e0d70202f69ffd2b38d58a76037274fe49a1cc79ec",
    "extract_dir": "LunaTranslator",
    "shortcuts": [
        [
            "LunaTranslator.exe",
            "LunaTranslator"
        ]
    ],
    "persist": [
        "userconfig",
        "resources"
    ],
    "checkver": "github",
    "autoupdate": {
        "url": "https://github.com/HIllya51/LunaTranslator/releases/download/v$version/LunaTranslator.zip"
    }
}
