{
    "version": "6.9.2",
    "description": "Galgame翻译工具, 支持剪贴板, OCR, HOOK, 支持30余种翻译工具, 支持TTS",
    "homepage": "https://github.com/HIllya51/LunaTranslator",
    "license": "GPL-3.0-only",
    "url": "https://github.com/HIllya51/LunaTranslator/releases/download/v6.9.2/LunaTranslator.zip",
    "hash": "a83841c2ce0cd25bafc540ebe16efbca225632a6fa6537bbfab83441ae5c6e5c",
    "extract_dir": "LunaTranslator",
    "shortcuts": [
        [
            "LunaTranslator.exe",
            "LunaTranslator"
        ]
    ],
    "persist": [
        "userconfig",
        "resources"
    ],
    "checkver": "github",
    "autoupdate": {
        "url": "https://github.com/HIllya51/LunaTranslator/releases/download/v$version/LunaTranslator.zip"
    }
}
