{
    "version": "20221011",
    "description": "mpv 懒人包",
    "homepage": "https://github.com/hooke007/MPV_lazy",
    "license": "GPL-2.0-only",
    "architecture": {
        "64bit": {
            "url": "https://github.com/hooke007/MPV_lazy/releases/download/20221011/mpv-lazy-20221011.exe#/dl.7z",
            "hash": "5934477863ad3b2ce88a6030a03d1fe0de9798f0da2de78539e2d8b790e7d0c8",
            "extract_dir": "mpv-lazy"
        }
    },
    "bin": [
        [
            "mpv.exe",
            "mpvlazy"
        ]
    ],
    "shortcuts": [
        [
            "mpv.exe",
            "mpvlazy"
        ]
    ],
    "checkver": "github",
    "autoupdate": {
        "architecture": {
            "64bit": {
                "url": "https://github.com/hooke007/MPV_lazy/releases/download/$version/mpv-lazy-$version.exe#/dl.7z"
            }
        }
    }
}
